LICENSE
MANIFEST.in
README.rst
setup.cfg
setup.py
QcloudApi/__init__.py
QcloudApi/__init__.pyc
QcloudApi/qcloudapi.py
QcloudApi/common/__init__.py
QcloudApi/common/api_exception.py
QcloudApi/common/request.py
QcloudApi/common/sign.py
QcloudApi/modules/__init__.py
QcloudApi/modules/account.py
QcloudApi/modules/apigateway.py
QcloudApi/modules/athena.py
QcloudApi/modules/base.py
QcloudApi/modules/batch.py
QcloudApi/modules/bgpip.py
QcloudApi/modules/bill.py
QcloudApi/modules/bm.py
QcloudApi/modules/bmeip.py
QcloudApi/modules/bmlb.py
QcloudApi/modules/bmvpc.py
QcloudApi/modules/cbs.py
QcloudApi/modules/ccr.py
QcloudApi/modules/ccs.py
QcloudApi/modules/cdb.py
QcloudApi/modules/cdn.py
QcloudApi/modules/cloudaudit.py
QcloudApi/modules/cmem.py
QcloudApi/modules/cns.py
QcloudApi/modules/cvm.py
QcloudApi/modules/dc.py
QcloudApi/modules/dfw.py
QcloudApi/modules/eip.py
QcloudApi/modules/emr.py
QcloudApi/modules/feecenter.py
QcloudApi/modules/image.py
QcloudApi/modules/lb.py
QcloudApi/modules/live.py
QcloudApi/modules/market.py
QcloudApi/modules/monitor.py
QcloudApi/modules/partners.py
QcloudApi/modules/redis.py
QcloudApi/modules/scaling.py
QcloudApi/modules/scf.py
QcloudApi/modules/sec.py
QcloudApi/modules/snapshot.py
QcloudApi/modules/sts.py
QcloudApi/modules/tbaas.py
QcloudApi/modules/tdsql.py
QcloudApi/modules/tmt.py
QcloudApi/modules/trade.py
QcloudApi/modules/vod.py
QcloudApi/modules/vpc.py
QcloudApi/modules/wenzhi.py
QcloudApi/modules/yunsou.py
qcloudapi_sdk_python.egg-info/PKG-INFO
qcloudapi_sdk_python.egg-info/SOURCES.txt
qcloudapi_sdk_python.egg-info/dependency_links.txt
qcloudapi_sdk_python.egg-info/top_level.txt